bob/__init__.py
bob/archive.py
bob/audit.py
bob/builder.py
bob/errors.py
bob/input.py
bob/intermediate.py
bob/invoker.py
bob/languages.py
bob/layers.py
bob/pathspec.py
bob/scripts.py
bob/share.py
bob/state.py
bob/stringparser.py
bob/tty.py
bob/utils.py
bob/version.py
bob/webdav.py
bob/cmds/__init__.py
bob/cmds/archive.py
bob/cmds/graph.py
bob/cmds/help.py
bob/cmds/helpers.py
bob/cmds/invoke.py
bob/cmds/layers.py
bob/cmds/misc.py
bob/cmds/show.py
bob/cmds/build/__init__.py
bob/cmds/build/build.py
bob/cmds/build/clean.py
bob/cmds/build/project.py
bob/cmds/build/query.py
bob/cmds/build/state.py
bob/cmds/build/status.py
bob/cmds/jenkins/__init__.py
bob/cmds/jenkins/exec.py
bob/cmds/jenkins/intermediate.py
bob/cmds/jenkins/jenkins.py
bob/generators/EclipseCdtGenerator.py
bob/generators/QtCreatorGenerator.py
bob/generators/VisualStudio.py
bob/generators/VisualStudioCode.py
bob/generators/__init__.py
bob/generators/common.py
bob/scm/__init__.py
bob/scm/cvs.py
bob/scm/git.py
bob/scm/imp.py
bob/scm/scm.py
bob/scm/svn.py
bob/scm/url.py
bobbuildtool-1.2.0.data/data/bin/bob-namespace-sandbox
bobbuildtool-1.2.0.data/data/share/bash-completion/completions/bob
bobbuildtool-1.2.0.data/data/share/man/man1/bob-archive.1
bobbuildtool-1.2.0.data/data/share/man/man1/bob-build.1
bobbuildtool-1.2.0.data/data/share/man/man1/bob-clean.1
bobbuildtool-1.2.0.data/data/share/man/man1/bob-dev.1
bobbuildtool-1.2.0.data/data/share/man/man1/bob-graph.1
bobbuildtool-1.2.0.data/data/share/man/man1/bob-init.1
bobbuildtool-1.2.0.data/data/share/man/man1/bob-jenkins.1
bobbuildtool-1.2.0.data/data/share/man/man1/bob-layers.1
bobbuildtool-1.2.0.data/data/share/man/man1/bob-ls-recipes.1
bobbuildtool-1.2.0.data/data/share/man/man1/bob-ls.1
bobbuildtool-1.2.0.data/data/share/man/man1/bob-project.1
bobbuildtool-1.2.0.data/data/share/man/man1/bob-query-meta.1
bobbuildtool-1.2.0.data/data/share/man/man1/bob-query-path.1
bobbuildtool-1.2.0.data/data/share/man/man1/bob-query-recipe.1
bobbuildtool-1.2.0.dist-info/licenses/LICENSE
bobbuildtool-1.2.0.dist-info/METADATA
bobbuildtool-1.2.0.dist-info/WHEEL
bobbuildtool-1.2.0.dist-info/entry_points.txt
bobbuildtool-1.2.0.dist-info/top_level.txt
bobbuildtool-1.2.0.dist-info/RECORD
