Metadata-Version: 2.4
Name: BobBuildTool
Version: 1.2.0
Summary: Functional cross platform build-automation tool
Home-page: https://bobbuildtool.github.io/
Download-URL: https://github.com/BobBuildTool/bob/releases
Author: Jan Klötzke
Author-email: jan@kloetzke.net
License: GPLv3+
Keywords: bob build-automation build-system
Classifier: Development Status :: 5 - Production/Stable
Classifier: Environment :: Console
Classifier: Intended Audience :: Developers
Classifier: License :: OSI Approved :: GNU General Public License v3 or later (GPLv3+)
Classifier: Operating System :: Microsoft :: Windows
Classifier: Operating System :: POSIX
Classifier: Programming Language :: Python :: 3 :: Only
Classifier: Topic :: Software Development :: Build Tools
Requires-Python: >=3.9
License-File: LICENSE
Requires-Dist: PyYAML
Requires-Dist: schema
Requires-Dist: python-magic
Requires-Dist: pyparsing>=3
Provides-Extra: azure
Requires-Dist: azure-storage-blob; extra == "azure"
Dynamic: author
Dynamic: author-email
Dynamic: classifier
Dynamic: description
Dynamic: description-content-type
Dynamic: download-url
Dynamic: home-page
Dynamic: keywords
Dynamic: license
Dynamic: license-file
Dynamic: provides-extra
Dynamic: requires-dist
Dynamic: requires-python
Dynamic: summary
